flywheel_migration/__init__.py
flywheel_migration/bruker.py
flywheel_migration/dcm.py
flywheel_migration/parrec.py
flywheel_migration/parrec_headers.py
flywheel_migration/pfile.py
flywheel_migration/util.py
flywheel_migration/deidentify/__init__.py
flywheel_migration/deidentify/csv_subject_map.py
flywheel_migration/deidentify/deid-profiles.yml
flywheel_migration/deidentify/deid_field.py
flywheel_migration/deidentify/deid_log.py
flywheel_migration/deidentify/deid_profile.py
flywheel_migration/deidentify/dicom_file_profile.py
flywheel_migration/deidentify/exceptions.py
flywheel_migration/deidentify/factory.py
flywheel_migration/deidentify/file_profile.py
flywheel_migration/deidentify/filename_file_profile.py
flywheel_migration/deidentify/jpg_file_profile.py
flywheel_migration/deidentify/json_file_profile.py
flywheel_migration/deidentify/key_value_text_file_profile.py
flywheel_migration/deidentify/nifti_file_profile.py
flywheel_migration/deidentify/png_file_profile.py
flywheel_migration/deidentify/subject_map.py
flywheel_migration/deidentify/table_file_profile.py
flywheel_migration/deidentify/tiff_file_profile.py
flywheel_migration/deidentify/validation.py
flywheel_migration/deidentify/xml_file_profile.py
flywheel_migration/deidentify/zip_archive_profile.py
flywheel_migration-13.10.5.dist-info/METADATA
flywheel_migration-13.10.5.dist-info/WHEEL
flywheel_migration-13.10.5.dist-info/licenses/LICENSE
flywheel_migration-13.10.5.dist-info/RECORD
