Metadata-Version: 2.4
Name: flywheel-migration
Version: 13.10.5
Summary: Flywheel Migration Toolkit
Project-URL: Homepage, https://gitlab.com/flywheel-io/public/migration-toolkit
Project-URL: Repository, https://gitlab.com/flywheel-io/public/migration-toolkit
Project-URL: Documentation, https://gitlab.com/flywheel-io/public/migration-toolkit
Author-email: Flywheel <support@flywheel.io>
License-Expression: MIT
License-File: LICENSE
Keywords: Flywheel,data,flywheel,migration,toolkit
Requires-Python: ~=3.10.0
Requires-Dist: dotty-dict~=1.3
Requires-Dist: fs~=2.4
Requires-Dist: fw-file~=4.2.1
Requires-Dist: lxml~=5.4
Requires-Dist: nibabel~=5.3
Requires-Dist: pandas~=2.2
Requires-Dist: pathvalidate<4,>=2.5.2
Requires-Dist: piexif~=1.1
Requires-Dist: pillow<12,>=10.4.0
Requires-Dist: pycryptodome~=3.23
Requires-Dist: pypng<1,>=0
Requires-Dist: python-dateutil~=2.9
Requires-Dist: pytz
Requires-Dist: pyyaml<7,>=6.0.2
Requires-Dist: tzlocal~=5.3
Provides-Extra: all
Requires-Dist: deid<0.5,>=0.4; extra == 'all'
Provides-Extra: pixel
Requires-Dist: deid<0.5,>=0.4; extra == 'pixel'
